dataforge/__init__.py
dataforge/backtest.py
dataforge/collector.py
dataforge/database.py
dataforge/tools.py
dataforgelab-0.1.2.dist-info/METADATA
dataforgelab-0.1.2.dist-info/WHEEL
dataforgelab-0.1.2.dist-info/top_level.txt
dataforgelab-0.1.2.dist-info/RECORD
