Metadata-Version: 2.1
Name: dataforgelab
Version: 0.1.2
Summary: Quantitative Copilot - a helper in quant developping
Home-page: https://github.com/ppoak/dataforge
Author: ppoak
Author-email: ppoak@foxmail.com
Keywords: quant,framework,finance
Requires-Dist: bs4
Requires-Dist: numpy
Requires-Dist: joblib
Requires-Dist: pandas
Requires-Dist: akshare
Requires-Dist: backtrader
Requires-Dist: matplotlib
